{
	"entities": [
		{
			"name": "file0.ts",
			"type": "file",
			"id": 0,
			"fullname": "I:\\Pro.soft\\ENRE\\ENRE-ts\\tests\\cases\\_extend-declaration\\_interface-extends-merging\\file0.ts"
		},
		{
			"name": "Foo",
			"type": "interface",
			"id": 1,
			"fullname": "Foo",
			"location": {
				"start": {
					"line": 1,
					"column": 11
				},
				"end": {
					"line": 1,
					"column": 14
				}
			}
		},
		{
			"name": "prop0",
			"type": "property",
			"id": 2,
			"fullname": "Foo.prop0",
			"location": {
				"start": {
					"line": 2,
					"column": 5
				},
				"end": {
					"line": 2,
					"column": 10
				}
			}
		},
		{
			"name": "Bar",
			"type": "interface",
			"id": 3,
			"fullname": "Bar",
			"location": {
				"start": {
					"line": 5,
					"column": 11
				},
				"end": {
					"line": 5,
					"column": 14
				}
			}
		},
		{
			"name": "prop1",
			"type": "property",
			"id": 4,
			"fullname": "Bar.prop1",
			"location": {
				"start": {
					"line": 6,
					"column": 5
				},
				"end": {
					"line": 6,
					"column": 10
				}
			}
		},
		{
			"name": "Baz",
			"type": "interface",
			"id": 5,
			"fullname": "Baz",
			"location": {
				"start": {
					"line": 9,
					"column": 11
				},
				"end": {
					"line": 9,
					"column": 14
				}
			}
		},
		{
			"name": "prop2",
			"type": "property",
			"id": 6,
			"fullname": "Baz.prop2",
			"location": {
				"start": {
					"line": 10,
					"column": 5
				},
				"end": {
					"line": 10,
					"column": 10
				}
			}
		},
		{
			"name": "prop3",
			"type": "property",
			"id": 7,
			"fullname": "Baz.prop3",
			"location": {
				"start": {
					"line": 14,
					"column": 5
				},
				"end": {
					"line": 14,
					"column": 10
				}
			}
		}
	],
	"relations": [
		{
			"from": 5,
			"to": 1,
			"type": "extend",
			"location": {
				"start": {
					"line": 9,
					"column": 23
				}
			}
		},
		{
			"from": 5,
			"to": 3,
			"type": "extend",
			"location": {
				"start": {
					"line": 13,
					"column": 23
				}
			}
		}
	]
}